{
  "users": [
    {
      "id": "wdWiH0E",
      "name": "romentosto",
      "password": "romen",
      "password2": "romen",
      "email": "romen@romen.com",
      "promo": false,
      "country": "Åland Islands",
      "city": "madrid"
    },
    {
      "id": "39zPnAz",
      "name": "bfdbdfb",
      "password": "qw123",
      "password2": "qw123",
      "email": "awdawd@dawdaw",
      "promo": true,
      "country": "Bahamas",
      "city": "wdadwa"
    },
    {
      "id": "svMqiHY",
      "name": "pepe",
      "password": "123",
      "password2": "123",
      "email": "pepe@pepe",
      "promo": true,
      "country": "Australia",
      "city": "awdawd"
    }
  ]
}